hdl/templates/lcd_controller.v
`timescale 1ns / 100ps

module lcd_controller # (
    parameter HORIZONTAL_BACK_PORCH = 10, // px
    parameter HORIZONTAL_FRONT_PORCH = 40, // px

    parameter VERTICAL_BACK_PORCH = 10, // lines
    parameter VERTICAL_FRONT_PORCH = 10, // lines

    parameter HORIZONTAL_DATA_WIDTH = 800, // px
    parameter VERTICAL_DATA_WIDTH = 480 // lines
)(
    input wire clk,
    input wire aresetn,
    input wire i_start,

    output wire     o_data_en,
    output wire[7:0] o_red,
    output wire[7:0] o_green,
    output wire[7:0] o_blue
);
    parameter IDLE = 0;

    parameter CTRL_VBP  = 2'b01;
    parameter CTRL_DATA = 2'b10;
    parameter CTRL_VFP  = 2'b11;
    reg[1:0] controller_state;

    parameter LINE_HBP  = 2'b01;
    parameter LINE_DATA = 2'b10;
    parameter LINE_HFP  = 2'b11;
    reg[1:0] line_state;
    reg[8:0] line_count;
    reg[9:0] px_count;

    assign o_data_en = (controller_state == CTRL_DATA) && (line_state == LINE_DATA);
    assign o_red = 8'h00;
    assign o_green = 8'h00;
    assign o_blue = o_data_en ? 8'hFF : 8'h00;

    // this module works at negedge
    // the lcd reads at posedge
    // allows us to meet hold and setup for lcd
    // easily
    always @(negedge clk) begin
        if (!aresetn) begin
            controller_state <= IDLE;
            line_state <= IDLE;
            px_count <= 0;
            line_count <= 0;
        end
        else if (controller_state == IDLE) begin
            // stay in idle until start
            if (i_start) begin
                controller_state <= CTRL_VBP;
                line_state <= LINE_HBP;
                px_count <= 0;
            end
        end
        else begin
            case (line_state)
                IDLE: begin
                    line_state <= LINE_HBP;
                    px_count <= 0;
                    line_count <= 0;
                end
                LINE_HBP: begin
                    if (px_count >= HORIZONTAL_BACK_PORCH - 1) begin
                        line_state <= LINE_DATA;
                        px_count <= 0;
                    end
                    else begin
                        px_count <= px_count + 1;
                    end
                end
                LINE_DATA: begin
                    if (px_count >= HORIZONTAL_DATA_WIDTH - 1) begin
                        line_state <= LINE_HFP;
                        px_count <= 0;
                    end
                    else begin
                        px_count <= px_count + 1;
                    end
                end
                LINE_HFP: begin
                    if (px_count >= HORIZONTAL_FRONT_PORCH - 1) begin
                        px_count <= 0;
                        case (controller_state)
                            CTRL_VBP: begin
                                line_state <= LINE_HBP;
                                if (line_count == VERTICAL_BACK_PORCH - 1) begin
                                    line_count <= 0;
                                    controller_state <= CTRL_DATA;
                                end
                                else begin
                                    line_count <= line_count + 1;
                                end
                            end
                            CTRL_DATA: begin
                                line_state <= LINE_HBP;
                                if (line_count == VERTICAL_DATA_WIDTH - 1) begin
                                    line_count <= 0;
                                    controller_state <= CTRL_VFP;
                                end
                                else begin
                                    line_count <= line_count + 1;
                                end
                            end
                            CTRL_VFP: begin
                                if (line_count == VERTICAL_FRONT_PORCH - 1) begin
                                    // frame done
                                    line_count <= 0;
                                    controller_state <= IDLE;
                                    line_state <= IDLE;
                                end
                                else begin
                                    line_count <= line_count + 1;
                                end
                            end
                        endcase
                    end
                    else begin
                        px_count <= px_count + 1;
                    end
                end
            endcase
        end
    end

endmodule

lcd_tb.v
`timescale 1ns/1ps

module tb_lcd_controller;

    // Clock and reset
    reg clk;
    reg aresetn;
    reg i_start;

    // Outputs from DUT
    wire o_data_en;
    wire [7:0] o_red;
    wire [7:0] o_green;
    wire [7:0] o_blue;

    // Clock generation: 10ns period => 100 MHz
    initial clk = 0;
    always #5 clk = ~clk;

    initial begin
        $dumpfile("wave.vcd");
        $dumpvars(0);
    end

    // Instantiate the DUT
    lcd_controller #(
        .HORIZONTAL_BACK_PORCH(10), // px
        .HORIZONTAL_FRONT_PORCH(20), // px
        
        .VERTICAL_BACK_PORCH(10), // lines
        .VERTICAL_FRONT_PORCH(20), // lines

        .HORIZONTAL_DATA_WIDTH(20), // px
        .VERTICAL_DATA_WIDTH(20) // px
    ) dut (
        .clk(clk),
        .aresetn(aresetn),
        .i_start(i_start),
        .o_data_en(o_data_en),
        .o_red(o_red),
        .o_green(o_green),
        .o_blue(o_blue)
    );

    // Test procedure
    initial begin
        $display("Starting LCD controller testbench...");

        // Initial conditions
        aresetn = 0;
        i_start = 0;

        // Wait a few cycles and deassert reset
        #20;
        aresetn = 1;

        // Wait a few cycles before starting
        #20;
        i_start = 1;

        #10;
        i_start = 0;

        // Run simulation long enough to complete a frame
        #100000;

        $display("Finished simulation.");
        $finish;
    end

    // Monitor important outputs
    always @(posedge clk) begin
        if (o_data_en)
            $display("Time: %0t | DATA ENABLED | Blue: %02X", $time, o_blue);
    end

endmodule

wave.vcd
$date
	Sun Aug  3 13:25:02 2025
$end
$version
	Icarus Verilog
$end
$timescale
	1ps
$end
$scope module tb_lcd_controller $end
$var wire 8 ! o_green [7:0] $end
$var wire 8 " o_red [7:0] $end
$var wire 1 # o_data_en $end
$var wire 8 $ o_blue [7:0] $end
$var reg 1 % aresetn $end
$var reg 1 & clk $end
$var reg 1 ' i_start $end
$scope module dut $end
$var wire 1 % aresetn $end
$var wire 1 & clk $end
$var wire 1 ' i_start $end
$var wire 1 # o_data_en $end
$var wire 8 ( o_green [7:0] $end
$var wire 8 ) o_red [7:0] $end
$var wire 8 * o_blue [7:0] $end
$var reg 2 + controller_state [1:0] $end
$var reg 9 , line_count [8:0] $end
$var reg 2 - line_state [1:0] $end
$var reg 10 . px_count [9:0] $end
$upscope $end
$upscope $end
$enddefinitions $end
#0
$dumpvars
b0 .
b0 -
b0 ,
b0 +
b0 *
b0 )
b0 (
0'
0&
0%
b0 $
0#
b0 "
b0 !
$end
#5000
1&
#10000
0&
#15000
1&
#20000
0&
1%
#25000
1&
#30000
0&
#35000
1&
#40000
b1 -
b1 +
0&
1'
#45000
1&
#50000
b1 .
0&
0'
#55000
1&
#60000
b10 .
0&
#65000
1&
#70000
b11 .
0&
#75000
1&
#80000
b100 .
0&
#85000
1&
#90000
b101 .
0&
#95000
1&
#100000
b110 .
0&
#105000
1&
#110000
b111 .
0&
#115000
1&
#120000
b1000 .
0&
#125000
1&
#130000
b1001 .
0&
#135000
1&
#140000
b0 .
b10 -
0&
#145000
1&
#150000
b1 .
0&
#155000
1&
#160000
b10 .
0&
#165000
1&
#170000
b11 .
0&
#175000
1&
#180000
b100 .
0&
#185000
1&
#190000
b101 .
0&
#195000
1&
#200000
b110 .
0&
#205000
1&
#210000
b111 .
0&
#215000
1&
#220000
b1000 .
0&
#225000
1&
#230000
b1001 .
0&
#235000
1&
#240000
b1010 .
0&
#245000
1&
#250000
b1011 .
0&
#255000
1&
#260000
b1100 .
0&
#265000
1&
#270000
b1101 .
0&
#275000
1&
#280000
b1110 .
0&
#285000
1&
#290000
b1111 .
0&
#295000
1&
#300000
b10000 .
0&
#305000
1&
#310000
b10001 .
0&
#315000
1&
#320000
b10010 .
0&
#325000
1&
#330000
b10011 .
0&
#335000
1&
#340000
b0 .
b11 -
0&
#345000
1&
#350000
b1 .
0&
#355000
1&
#360000
b10 .
0&
#365000
1&
#370000
b11 .
0&
#375000
1&
#380000
b100 .
0&
#385000
1&
#390000
b101 .
0&
#395000
1&
#400000
b110 .
0&
#405000
1&
#410000
b111 .
0&
#415000
1&
#420000
b1000 .
0&
#425000
1&
#430000
b1001 .
0&
#435000
1&
#440000
b1010 .
0&
#445000
1&
#450000
b1011 .
0&
#455000
1&
#460000
b1100 .
0&
#465000
1&
#470000
b1101 .
0&
#475000
1&
#480000
b1110 .
0&
#485000
1&
#490000
b1111 .
0&
#495000
1&
#500000
b10000 .
0&
#505000
1&
#510000
b10001 .
0&
#515000
1&
#520000
b10010 .
0&
#525000
1&
#530000
b10011 .
0&
#535000
1&
#540000
b1 ,
b1 -
b0 .
0&
#545000
1&
#550000
b1 .
0&
#555000
1&
#560000
b10 .
0&
#565000
1&
#570000
b11 .
0&
#575000
1&
#580000
b100 .
0&
#585000
1&
#590000
b101 .
0&
#595000
1&
#600000
b110 .
0&
#605000
1&
#610000
b111 .
0&
#615000
1&
#620000
b1000 .
0&
#625000
1&
#630000
b1001 .
0&
#635000
1&
#640000
b0 .
b10 -
0&
#645000
1&
#650000
b1 .
0&
#655000
1&
#660000
b10 .
0&
#665000
1&
#670000
b11 .
0&
#675000
1&
#680000
b100 .
0&
#685000
1&
#690000
b101 .
0&
#695000
1&
#700000
b110 .
0&
#705000
1&
#710000
b111 .
0&
#715000
1&
#720000
b1000 .
0&
#725000
1&
#730000
b1001 .
0&
#735000
1&
#740000
b1010 .
0&
#745000
1&
#750000
b1011 .
0&
#755000
1&
#760000
b1100 .
0&
#765000
1&
#770000
b1101 .
0&
#775000
1&
#780000
b1110 .
0&
#785000
1&
#790000
b1111 .
0&
#795000
1&
#800000
b10000 .
0&
#805000
1&
#810000
b10001 .
0&
#815000
1&
#820000
b10010 .
0&
#825000
1&
#830000
b10011 .
0&
#835000
1&
#840000
b0 .
b11 -
0&
#845000
1&
#850000
b1 .
0&
#855000
1&
#860000
b10 .
0&
#865000
1&
#870000
b11 .
0&
#875000
1&
#880000
b100 .
0&
#885000
1&
#890000
b101 .
0&
#895000
1&
#900000
b110 .
0&
#905000
1&
#910000
b111 .
0&
#915000
1&
#920000
b1000 .
0&
#925000
1&
#930000
b1001 .
0&
#935000
1&
#940000
b1010 .
0&
#945000
1&
#950000
b1011 .
0&
#955000
1&
#960000
b1100 .
0&
#965000
1&
#970000
b1101 .
0&
#975000
1&
#980000
b1110 .
0&
#985000
1&
#990000
b1111 .
0&
#995000
1&
#1000000
b10000 .
0&
#1005000
1&
#1010000
b10001 .
0&
#1015000
1&
#1020000
b10010 .
0&
#1025000
1&
#1030000
b10011 .
0&
#1035000
1&
#1040000
b10 ,
b1 -
b0 .
0&
#1045000
1&
#1050000
b1 .
0&
#1055000
1&
#1060000
b10 .
0&
#1065000
1&
#1070000
b11 .
0&
#1075000
1&
#1080000
b100 .
0&
#1085000
1&
#1090000
b101 .
0&
#1095000
1&
#1100000
b110 .
0&
#1105000
1&
#1110000
b111 .
0&
#1115000
1&
#1120000
b1000 .
0&
#1125000
1&
#1130000
b1001 .
0&
#1135000
1&
#1140000
b0 .
b10 -
0&
#1145000
1&
#1150000
b1 .
0&
#1155000
1&
#1160000
b10 .
0&
#1165000
1&
#1170000
b11 .
0&
#1175000
1&
#1180000
b100 .
0&
#1185000
1&
#1190000
b101 .
0&
#1195000
1&
#1200000
b110 .
0&
#1205000
1&
#1210000
b111 .
0&
#1215000
1&
#1220000
b1000 .
0&
#1225000
1&
#1230000
b1001 .
0&
#1235000
1&
#1240000
b1010 .
0&
#1245000
1&
#1250000
b1011 .
0&
#1255000
1&
#1260000
b1100 .
0&
#1265000
1&
#1270000
b1101 .
0&
#1275000
1&
#1280000
b1110 .
0&
#1285000
1&
#1290000
b1111 .
0&
#1295000
1&
#1300000
b10000 .
0&
#1305000
1&
#1310000
b10001 .
0&
#1315000
1&
#1320000
b10010 .
0&
#1325000
1&
#1330000
b10011 .
0&
#1335000
1&
#1340000
b0 .
b11 -
0&
#1345000
1&
#1350000
b1 .
0&
#1355000
1&
#1360000
b10 .
0&
#1365000
1&
#1370000
b11 .
0&
#1375000
1&
#1380000
b100 .
0&
#1385000
1&
#1390000
b101 .
0&
#1395000
1&
#1400000
b110 .
0&
#1405000
1&
#1410000
b111 .
0&
#1415000
1&
#1420000
b1000 .
0&
#1425000
1&
#1430000
b1001 .
0&
#1435000
1&
#1440000
b1010 .
0&
#1445000
1&
#1450000
b1011 .
0&
#1455000
1&
#1460000
b1100 .
0&
#1465000
1&
#1470000
b1101 .
0&
#1475000
1&
#1480000
b1110 .
0&
#1485000
1&
#1490000
b1111 .
0&
#1495000
1&
#1500000
b10000 .
0&
#1505000
1&
#1510000
b10001 .
0&
#1515000
1&
#1520000
b10010 .
0&
#1525000
1&
#1530000
b10011 .
0&
#1535000
1&
#1540000
b11 ,
b1 -
b0 .
0&
#1545000
1&
#1550000
b1 .
0&
#1555000
1&
#1560000
b10 .
0&
#1565000
1&
#1570000
b11 .
0&
#1575000
1&
#1580000
b100 .
0&
#1585000
1&
#1590000
b101 .
0&
#1595000
1&
#1600000
b110 .
0&
#1605000
1&
#1610000
b111 .
0&
#1615000
1&
#1620000
b1000 .
0&
#1625000
1&
#1630000
b1001 .
0&
#1635000
1&
#1640000
b0 .
b10 -
0&
#1645000
1&
#1650000
b1 .
0&
#1655000
1&
#1660000
b10 .
0&
#1665000
1&
#1670000
b11 .
0&
#1675000
1&
#1680000
b100 .
0&
#1685000
1&
#1690000
b101 .
0&
#1695000
1&
#1700000
b110 .
0&
#1705000
1&
#1710000
b111 .
0&
#1715000
1&
#1720000
b1000 .
0&
#1725000
1&
#1730000
b1001 .
0&
#1735000
1&
#1740000
b1010 .
0&
#1745000
1&
#1750000
b1011 .
0&
#1755000
1&
#1760000
b1100 .
0&
#1765000
1&
#1770000
b1101 .
0&
#1775000
1&
#1780000
b1110 .
0&
#1785000
1&
#1790000
b1111 .
0&
#1795000
1&
#1800000
b10000 .
0&
#1805000
1&
#1810000
b10001 .
0&
#1815000
1&
#1820000
b10010 .
0&
#1825000
1&
#1830000
b10011 .
0&
#1835000
1&
#1840000
b0 .
b11 -
0&
#1845000
1&
#1850000
b1 .
0&
#1855000
1&
#1860000
b10 .
0&
#1865000
1&
#1870000
b11 .
0&
#1875000
1&
#1880000
b100 .
0&
#1885000
1&
#1890000
b101 .
0&
#1895000
1&
#1900000
b110 .
0&
#1905000
1&
#1910000
b111 .
0&
#1915000
1&
#1920000
b1000 .
0&
#1925000
1&
#1930000
b1001 .
0&
#1935000
1&
#1940000
b1010 .
0&
#1945000
1&
#1950000
b1011 .
0&
#1955000
1&
#1960000
b1100 .
0&
#1965000
1&
#1970000
b1101 .
0&
#1975000
1&
#1980000
b1110 .
0&
#1985000
1&
#1990000
b1111 .
0&
#1995000
1&
#2000000
b10000 .
0&
#2005000
1&
#2010000
b10001 .
0&
#2015000
1&
#2020000
b10010 .
0&
#2025000
1&
#2030000
b10011 .
0&
#2035000
1&
#2040000
b100 ,
b1 -
b0 .
0&
#2045000
1&
#2050000
b1 .
0&
#2055000
1&
#2060000
b10 .
0&
#2065000
1&
#2070000
b11 .
0&
#2075000
1&
#2080000
b100 .
0&
#2085000
1&
#2090000
b101 .
0&
#2095000
1&
#2100000
b110 .
0&
#2105000
1&
#2110000
b111 .
0&
#2115000
1&
#2120000
b1000 .
0&
#2125000
1&
#2130000
b1001 .
0&
#2135000
1&
#2140000
b0 .
b10 -
0&
#2145000
1&
#2150000
b1 .
0&
#2155000
1&
#2160000
b10 .
0&
#2165000
1&
#2170000
b11 .
0&
#2175000
1&
#2180000
b100 .
0&
#2185000
1&
#2190000
b101 .
0&
#2195000
1&
#2200000
b110 .
0&
#2205000
1&
#2210000
b111 .
0&
#2215000
1&
#2220000
b1000 .
0&
#2225000
1&
#2230000
b1001 .
0&
#2235000
1&
#2240000
b1010 .
0&
#2245000
1&
#2250000
b1011 .
0&
#2255000
1&
#2260000
b1100 .
0&
#2265000
1&
#2270000
b1101 .
0&
#2275000
1&
#2280000
b1110 .
0&
#2285000
1&
#2290000
b1111 .
0&
#2295000
1&
#2300000
b10000 .
0&
#2305000
1&
#2310000
b10001 .
0&
#2315000
1&
#2320000
b10010 .
0&
#2325000
1&
#2330000
b10011 .
0&
#2335000
1&
#2340000
b0 .
b11 -
0&
#2345000
1&
#2350000
b1 .
0&
#2355000
1&
#2360000
b10 .
0&
#2365000
1&
#2370000
b11 .
0&
#2375000
1&
#2380000
b100 .
0&
#2385000
1&
#2390000
b101 .
0&
#2395000
1&
#2400000
b110 .
0&
#2405000
1&
#2410000
b111 .
0&
#2415000
1&
#2420000
b1000 .
0&
#2425000
1&
#2430000
b1001 .
0&
#2435000
1&
#2440000
b1010 .
0&
#2445000
1&
#2450000
b1011 .
0&
#2455000
1&
#2460000
b1100 .
0&
#2465000
1&
#2470000
b1101 .
0&
#2475000
1&
#2480000
b1110 .
0&
#2485000
1&
#2490000
b1111 .
0&
#2495000
1&
#2500000
b10000 .
0&
#2505000
1&
#2510000
b10001 .
0&
#2515000
1&
#2520000
b10010 .
0&
#2525000
1&
#2530000
b10011 .
0&
#2535000
1&
#2540000
b101 ,
b1 -
b0 .
0&
#2545000
1&
#2550000
b1 .
0&
#2555000
1&
#2560000
b10 .
0&
#2565000
1&
#2570000
b11 .
0&
#2575000
1&
#2580000
b100 .
0&
#2585000
1&
#2590000
b101 .
0&
#2595000
1&
#2600000
b110 .
0&
#2605000
1&
#2610000
b111 .
0&
#2615000
1&
#2620000
b1000 .
0&
#2625000
1&
#2630000
b1001 .
0&
#2635000
1&
#2640000
b0 .
b10 -
0&
#2645000
1&
#2650000
b1 .
0&
#2655000
1&
#2660000
b10 .
0&
#2665000
1&
#2670000
b11 .
0&
#2675000
1&
#2680000
b100 .
0&
#2685000
1&
#2690000
b101 .
0&
#2695000
1&
#2700000
b110 .
0&
#2705000
1&
#2710000
b111 .
0&
#2715000
1&
#2720000
b1000 .
0&
#2725000
1&
#2730000
b1001 .
0&
#2735000
1&
#2740000
b1010 .
0&
#2745000
1&
#2750000
b1011 .
0&
#2755000
1&
#2760000
b1100 .
0&
#2765000
1&
#2770000
b1101 .
0&
#2775000
1&
#2780000
b1110 .
0&
#2785000
1&
#2790000
b1111 .
0&
#2795000
1&
#2800000
b10000 .
0&
#2805000
1&
#2810000
b10001 .
0&
#2815000
1&
#2820000
b10010 .
0&
#2825000
1&
#2830000
b10011 .
0&
#2835000
1&
#2840000
b0 .
b11 -
0&
#2845000
1&
#2850000
b1 .
0&
#2855000
1&
#2860000
b10 .
0&
#2865000
1&
#2870000
b11 .
0&
#2875000
1&
#2880000
b100 .
0&
#2885000
1&
#2890000
b101 .
0&
#2895000
1&
#2900000
b110 .
0&
#2905000
1&
#2910000
b111 .
0&
#2915000
1&
#2920000
b1000 .
0&
#2925000
1&
#2930000
b1001 .
0&
#2935000
1&
#2940000
b1010 .
0&
#2945000
1&
#2950000
b1011 .
0&
#2955000
1&
#2960000
b1100 .
0&
#2965000
1&
#2970000
b1101 .
0&
#2975000
1&
#2980000
b1110 .
0&
#2985000
1&
#2990000
b1111 .
0&
#2995000
1&
#3000000
b10000 .
0&
#3005000
1&
#3010000
b10001 .
0&
#3015000
1&
#3020000
b10010 .
0&
#3025000
1&
#3030000
b10011 .
0&
#3035000
1&
#3040000
b110 ,
b1 -
b0 .
0&
#3045000
1&
#3050000
b1 .
0&
#3055000
1&
#3060000
b10 .
0&
#3065000
1&
#3070000
b11 .
0&
#3075000
1&
#3080000
b100 .
0&
#3085000
1&
#3090000
b101 .
0&
#3095000
1&
#3100000
b110 .
0&
#3105000
1&
#3110000
b111 .
0&
#3115000
1&
#3120000
b1000 .
0&
#3125000
1&
#3130000
b1001 .
0&
#3135000
1&
#3140000
b0 .
b10 -
0&
#3145000
1&
#3150000
b1 .
0&
#3155000
1&
#3160000
b10 .
0&
#3165000
1&
#3170000
b11 .
0&
#3175000
1&
#3180000
b100 .
0&
#3185000
1&
#3190000
b101 .
0&
#3195000
1&
#3200000
b110 .
0&
#3205000
1&
#3210000
b111 .
0&
#3215000
1&
#3220000
b1000 .
0&
#3225000
1&
#3230000
b1001 .
0&
#3235000
1&
#3240000
b1010 .
0&
#3245000
1&
#3250000
b1011 .
0&
#3255000
1&
#3260000
b1100 .
0&
#3265000
1&
#3270000
b1101 .
0&
#3275000
1&
#3280000
b1110 .
0&
#3285000
1&
#3290000
b1111 .
0&
#3295000
1&
#3300000
b10000 .
0&
#3305000
1&
#3310000
b10001 .
0&
#3315000
1&
#3320000
b10010 .
0&
#3325000
1&
#3330000
b10011 .
0&
#3335000
1&
#3340000
b0 .
b11 -
0&
#3345000
1&
#3350000
b1 .
0&
#3355000
1&
#3360000
b10 .
0&
#3365000
1&
#3370000
b11 .
0&
#3375000
1&
#3380000
b100 .
0&
#3385000
1&
#3390000
b101 .
0&
#3395000
1&
#3400000
b110 .
0&
#3405000
1&
#3410000
b111 .
0&
#3415000
1&
#3420000
b1000 .
0&
#3425000
1&
#3430000
b1001 .
0&
#3435000
1&
#3440000
b1010 .
0&
#3445000
1&
#3450000
b1011 .
0&
#3455000
1&
#3460000
b1100 .
0&
#3465000
1&
#3470000
b1101 .
0&
#3475000
1&
#3480000
b1110 .
0&
#3485000
1&
#3490000
b1111 .
0&
#3495000
1&
#3500000
b10000 .
0&
#3505000
1&
#3510000
b10001 .
0&
#3515000
1&
#3520000
b10010 .
0&
#3525000
1&
#3530000
b10011 .
0&
#3535000
1&
#3540000
b111 ,
b1 -
b0 .
0&
#3545000
1&
#3550000
b1 .
0&
#3555000
1&
#3560000
b10 .
0&
#3565000
1&
#3570000
b11 .
0&
#3575000
1&
#3580000
b100 .
0&
#3585000
1&
#3590000
b101 .
0&
#3595000
1&
#3600000
b110 .
0&
#3605000
1&
#3610000
b111 .
0&
#3615000
1&
#3620000
b1000 .
0&
#3625000
1&
#3630000
b1001 .
0&
#3635000
1&
#3640000
b0 .
b10 -
0&
#3645000
1&
#3650000
b1 .
0&
#3655000
1&
#3660000
b10 .
0&
#3665000
1&
#3670000
b11 .
0&
#3675000
1&
#3680000
b100 .
0&
#3685000
1&
#3690000
b101 .
0&
#3695000
1&
#3700000
b110 .
0&
#3705000
1&
#3710000
b111 .
0&
#3715000
1&
#3720000
b1000 .
0&
#3725000
1&
#3730000
b1001 .
0&
#3735000
1&
#3740000
b1010 .
0&
#3745000
1&
#3750000
b1011 .
0&
#3755000
1&
#3760000
b1100 .
0&
#3765000
1&
#3770000
b1101 .
0&
#3775000
1&
#3780000
b1110 .
0&
#3785000
1&
#3790000
b1111 .
0&
#3795000
1&
#3800000
b10000 .
0&
#3805000
1&
#3810000
b10001 .
0&
#3815000
1&
#3820000
b10010 .
0&
#3825000
1&
#3830000
b10011 .
0&
#3835000
1&
#3840000
b0 .
b11 -
0&
#3845000
1&
#3850000
b1 .
0&
#3855000
1&
#3860000
b10 .
0&
#3865000
1&
#3870000
b11 .
0&
#3875000
1&
#3880000
b100 .
0&
#3885000
1&
#3890000
b101 .
0&
#3895000
1&
#3900000
b110 .
0&
#3905000
1&
#3910000
b111 .
0&
#3915000
1&
#3920000
b1000 .
0&
#3925000
1&
#3930000
b1001 .
0&
#3935000
1&
#3940000
b1010 .
0&
#3945000
1&
#3950000
b1011 .
0&
#3955000
1&
#3960000
b1100 .
0&
#3965000
1&
#3970000
b1101 .
0&
#3975000
1&
#3980000
b1110 .
0&
#3985000
1&
#3990000
b1111 .
0&
#3995000
1&
#4000000
b10000 .
0&
#4005000
1&
#4010000
b10001 .
0&
#4015000
1&
#4020000
b10010 .
0&
#4025000
1&
#4030000
b10011 .
0&
#4035000
1&
#4040000
b1000 ,
b1 -
b0 .
0&
#4045000
1&
#4050000
b1 .
0&
#4055000
1&
#4060000
b10 .
0&
#4065000
1&
#4070000
b11 .
0&
#4075000
1&
#4080000
b100 .
0&
#4085000
1&
#4090000
b101 .
0&
#4095000
1&
#4100000
b110 .
0&
#4105000
1&
#4110000
b111 .
0&
#4115000
1&
#4120000
b1000 .
0&
#4125000
1&
#4130000
b1001 .
0&
#4135000
1&
#4140000
b0 .
b10 -
0&
#4145000
1&
#4150000
b1 .
0&
#4155000
1&
#4160000
b10 .
0&
#4165000
1&
#4170000
b11 .
0&
#4175000
1&
#4180000
b100 .
0&
#4185000
1&
#4190000
b101 .
0&
#4195000
1&
#4200000
b110 .
0&
#4205000
1&
#4210000
b111 .
0&
#4215000
1&
#4220000
b1000 .
0&
#4225000
1&
#4230000
b1001 .
0&
#4235000
1&
#4240000
b1010 .
0&
#4245000
1&
#4250000
b1011 .
0&
#4255000
1&
#4260000
b1100 .
0&
#4265000
1&
#4270000
b1101 .
0&
#4275000
1&
#4280000
b1110 .
0&
#4285000
1&
#4290000
b1111 .
0&
#4295000
1&
#4300000
b10000 .
0&
#4305000
1&
#4310000
b10001 .
0&
#4315000
1&
#4320000
b10010 .
0&
#4325000
1&
#4330000
b10011 .
0&
#4335000
1&
#4340000
b0 .
b11 -
0&
#4345000
1&
#4350000
b1 .
0&
#4355000
1&
#4360000
b10 .
0&
#4365000
1&
#4370000
b11 .
0&
#4375000
1&
#4380000
b100 .
0&
#4385000
1&
#4390000
b101 .
0&
#4395000
1&
#4400000
b110 .
0&
#4405000
1&
#4410000
b111 .
0&
#4415000
1&
#4420000
b1000 .
0&
#4425000
1&
#4430000
b1001 .
0&
#4435000
1&
#4440000
b1010 .
0&
#4445000
1&
#4450000
b1011 .
0&
#4455000
1&
#4460000
b1100 .
0&
#4465000
1&
#4470000
b1101 .
0&
#4475000
1&
#4480000
b1110 .
0&
#4485000
1&
#4490000
b1111 .
0&
#4495000
1&
#4500000
b10000 .
0&
#4505000
1&
#4510000
b10001 .
0&
#4515000
1&
#4520000
b10010 .
0&
#4525000
1&
#4530000
b10011 .
0&
#4535000
1&
#4540000
b1001 ,
b1 -
b0 .
0&
#4545000
1&
#4550000
b1 .
0&
#4555000
1&
#4560000
b10 .
0&
#4565000
1&
#4570000
b11 .
0&
#4575000
1&
#4580000
b100 .
0&
#4585000
1&
#4590000
b101 .
0&
#4595000
1&
#4600000
b110 .
0&
#4605000
1&
#4610000
b111 .
0&
#4615000
1&
#4620000
b1000 .
0&
#4625000
1&
#4630000
b1001 .
0&
#4635000
1&
#4640000
b0 .
b10 -
0&
#4645000
1&
#4650000
b1 .
0&
#4655000
1&
#4660000
b10 .
0&
#4665000
1&
#4670000
b11 .
0&
#4675000
1&
#4680000
b100 .
0&
#4685000
1&
#4690000
b101 .
0&
#4695000
1&
#4700000
b110 .
0&
#4705000
1&
#4710000
b111 .
0&
#4715000
1&
#4720000
b1000 .
0&
#4725000
1&
#4730000
b1001 .
0&
#4735000
1&
#4740000
b1010 .
0&
#4745000
1&
#4750000
b1011 .
0&
#4755000
1&
#4760000
b1100 .
0&
#4765000
1&
#4770000
b1101 .
0&
#4775000
1&
#4780000
b1110 .
0&
#4785000
1&
#4790000
b1111 .
0&
#4795000
1&
#4800000
b10000 .
0&
#4805000
1&
#4810000
b10001 .
0&
#4815000
1&
#4820000
b10010 .
0&
#4825000
1&
#4830000
b10011 .
0&
#4835000
1&
#4840000
b0 .
b11 -
0&
#4845000
1&
#4850000
b1 .
0&
#4855000
1&
#4860000
b10 .
0&
#4865000
1&
#4870000
b11 .
0&
#4875000
1&
#4880000
b100 .
0&
#4885000
1&
#4890000
b101 .
0&
#4895000
1&
#4900000
b110 .
0&
#4905000
1&
#4910000
b111 .
0&
#4915000
1&
#4920000
b1000 .
0&
#4925000
1&
#4930000
b1001 .
0&
#4935000
1&
#4940000
b1010 .
0&
#4945000
1&
#4950000
b1011 .
0&
#4955000
1&
#4960000
b1100 .
0&
#4965000
1&
#4970000
b1101 .
0&
#4975000
1&
#4980000
b1110 .
0&
#4985000
1&
#4990000
b1111 .
0&
#4995000
1&
#5000000
b10000 .
0&
#5005000
1&
#5010000
b10001 .
0&
#5015000
1&
#5020000
b10010 .
0&
#5025000
1&
#5030000
b10011 .
0&
#5035000
1&
#5040000
b10 +
b0 ,
b1 -
b0 .
0&
#5045000
1&
#5050000
b1 .
0&
#5055000
1&
#5060000
b10 .
0&
#5065000
1&
#5070000
b11 .
0&
#5075000
1&
#5080000
b100 .
0&
#5085000
1&
#5090000
b101 .
0&
#5095000
1&
#5100000
b110 .
0&
#5105000
1&
#5110000
b111 .
0&
#5115000
1&
#5120000
b1000 .
0&
#5125000
1&
#5130000
b1001 .
0&
#5135000
1&
#5140000
b11111111 $
b11111111 *
1#
b0 .
b10 -
0&
#5145000
1&
#5150000
b1 .
0&
#5155000
1&
#5160000
b10 .
0&
#5165000
1&
#5170000
b11 .
0&
#5175000
1&
#5180000
b100 .
0&
#5185000
1&
#5190000
b101 .
0&
#5195000
1&
#5200000
b110 .
0&
#5205000
1&
#5210000
b111 .
0&
#5215000
1&
#5220000
b1000 .
0&
#5225000
1&
#5230000
b1001 .
0&
#5235000
1&
#5240000
b1010 .
0&
#5245000
1&
#5250000
b1011 .
0&
#5255000
1&
#5260000
b1100 .
0&
#5265000
1&
#5270000
b1101 .
0&
#5275000
1&
#5280000
b1110 .
0&
#5285000
1&
#5290000
b1111 .
0&
#5295000
1&
#5300000
b10000 .
0&
#5305000
1&
#5310000
b10001 .
0&
#5315000
1&
#5320000
b10010 .
0&
#5325000
1&
#5330000
b10011 .
0&
#5335000
1&
#5340000
b0 $
b0 *
0#
b0 .
b11 -
0&
#5345000
1&
#5350000
b1 .
0&
#5355000
1&
#5360000
b10 .
0&
#5365000
1&
#5370000
b11 .
0&
#5375000
1&
#5380000
b100 .
0&
#5385000
1&
#5390000
b101 .
0&
#5395000
1&
#5400000
b110 .
0&
#5405000
1&
#5410000
b111 .
0&
#5415000
1&
#5420000
b1000 .
0&
#5425000
1&
#5430000
b1001 .
0&
#5435000
1&
#5440000
b1010 .
0&
#5445000
1&
#5450000
b1011 .
0&
#5455000
1&
#5460000
b1100 .
0&
#5465000
1&
#5470000
b1101 .
0&
#5475000
1&
#5480000
b1110 .
0&
#5485000
1&
#5490000
b1111 .
0&
#5495000
1&
#5500000
b10000 .
0&
#5505000
1&
#5510000
b10001 .
0&
#5515000
1&
#5520000
b10010 .
0&
#5525000
1&
#5530000
b10011 .
0&
#5535000
1&
#5540000
b1 ,
b1 -
b0 .
0&
#5545000
1&
#5550000
b1 .
0&
#5555000
1&
#5560000
b10 .
0&
#5565000
1&
#5570000
b11 .
0&
#5575000
1&
#5580000
b100 .
0&
#5585000
1&
#5590000
b101 .
0&
#5595000
1&
#5600000
b110 .
0&
#5605000
1&
#5610000
b111 .
0&
#5615000
1&
#5620000
b1000 .
0&
#5625000
1&
#5630000
b1001 .
0&
#5635000
1&
